pointtree/__init__.py
pointtree/py.typed
pointtree/config/__init__.py
pointtree/config/_config.py
pointtree/evaluation/__init__.py
pointtree/evaluation/_metrics.py
pointtree/evaluation/_time_tracker.py
pointtree/evaluation/_timer.py
pointtree/instance_segmentation/__init__.py
pointtree/instance_segmentation/_instance_segmentation_algorithm.py
pointtree/instance_segmentation/_multi_stage_algorithm.py
pointtree/instance_segmentation/_priority_queue.py
pointtree/instance_segmentation/_utils.py
pointtree/io/__init__.py
pointtree/io/_base_point_cloud_reader.py
pointtree/io/_base_point_cloud_writer.py
pointtree/io/_csv_reader.py
pointtree/io/_csv_writer.py
pointtree/io/_las_reader.py
pointtree/io/_las_writer.py
pointtree/io/_point_cloud_io_data.py
pointtree/io/_point_cloud_reader.py
pointtree/io/_point_cloud_writer.py
pointtree/operations/__init__.py
pointtree/operations/_cloth_simulation_filtering.py
pointtree/operations/_create_digital_terrain_model.py
pointtree/operations/_knn_search.py
pointtree/operations/_make_labels_consecutive.py
pointtree/operations/_normalize_height.py
pointtree/operations/_pack_batch.py
pointtree/operations/_ravel_index.py
pointtree/operations/_voxel_downsampling.py
pointtree/visualization/__init__.py
pointtree/visualization/_color_palette.py
pointtree/visualization/_color_point_cloud.py
pointtree/visualization/_hex_to_rgb.py
pointtree/visualization/_save_tree_map.py
pointtree-0.1.0.dist-info/LICENSE
pointtree-0.1.0.dist-info/METADATA
pointtree-0.1.0.dist-info/WHEEL
pointtree-0.1.0.dist-info/top_level.txt
pointtree-0.1.0.dist-info/RECORD
