Metadata-Version: 2.1
Name: pointtree
Version: 0.1.0
Summary: A Python Package for Tree Instance Segmentation in 3D Point Clouds.
Author-email: Josafat-Mattias Burmeister <burmeister@uni-potsdam.de>
Maintainer-email: Josafat-Mattias Burmeister <burmeister@uni-potsdam.de>
License: MIT License
Project-URL: Homepage, https://github.com/ai4trees/pointtree
Project-URL: Documentation, https://ai4trees.github.io/pointtree/
Project-URL: Repository, https://github.com/ai4trees/pointtree.git
Project-URL: Issues, https://github.com/ai4trees/pointtree/issues
Project-URL: Changelog, https://ai4trees.github.io/pointtree/changelog
Keywords: tree,point cloud,segmentation
Classifier: Development Status :: 4 - Beta
Classifier: Intended Audience :: Science/Research
Classifier: License :: OSI Approved :: MIT License
Classifier: Programming Language :: Python
Classifier: Programming Language :: Python :: 3 :: Only
Classifier: Programming Language :: Python :: 3.9
Classifier: Programming Language :: Python :: 3.10
Classifier: Programming Language :: Python :: 3.11
Classifier: Programming Language :: Python :: 3.12
Classifier: Topic :: Scientific/Engineering :: Artificial Intelligence
Requires-Python: >=3.9
License-File: LICENSE
Requires-Dist: cloth-simulation-filter<2.0.0,>=1.1.5
Requires-Dist: laspy<3.0.0,>=2.0.0
Requires-Dist: numba<1.0.0,>=0.55.0
Requires-Dist: numba-kdtree<1.0.0,>=0.3.0
Requires-Dist: numpy<3.0.0,>=1.21.0
Requires-Dist: pandas<3.0.0,>=2.0.0
Requires-Dist: pyclesperanto-prototype<1.0.0,>=0.22.0
Requires-Dist: scipy<2.0.0,>=1.8.0
Requires-Dist: scikit-image<1.0.0,>=0.21.0
Requires-Dist: scikit-learn<2.0.0,>=1.2.0
Requires-Dist: torch<2.5.0,>=2.0.0
Requires-Dist: torch-cluster<2.0.0,>=1.6.0
Requires-Dist: torch-scatter<3.0.0,>=2.0.2
Provides-Extra: dev
Requires-Dist: black; extra == "dev"
Requires-Dist: mypy; extra == "dev"
Requires-Dist: pandas-stubs; extra == "dev"
Requires-Dist: pylint; extra == "dev"
Requires-Dist: pytest; extra == "dev"
Requires-Dist: pytest-cov; extra == "dev"
Requires-Dist: types-Pillow; extra == "dev"
Provides-Extra: docs
Requires-Dist: sphinx; extra == "docs"
Requires-Dist: sphinx-copybutton; extra == "docs"
Requires-Dist: sphinx-design; extra == "docs"
Requires-Dist: sphinx-docsearch; extra == "docs"
Requires-Dist: sphinxawesome-theme; extra == "docs"
Requires-Dist: sphinx-sitemap; extra == "docs"
Requires-Dist: sphinxcontrib-jsmath; extra == "docs"
Requires-Dist: sphinxcontrib-katex; extra == "docs"
Requires-Dist: sphinxcontrib-napoleon; extra == "docs"
Requires-Dist: sphinx-mdinclude; extra == "docs"
